b2bt/__init__.py
b2bt/main.py
pnu_b2bt-1.1.2.data/data/man/man1/b2bt.1.gz
pnu_b2bt-1.1.2.data/data/man/man5/b2bt.5.gz
pnu_b2bt-1.1.2.dist-info/License
pnu_b2bt-1.1.2.dist-info/METADATA
pnu_b2bt-1.1.2.dist-info/WHEEL
pnu_b2bt-1.1.2.dist-info/entry_points.txt
pnu_b2bt-1.1.2.dist-info/top_level.txt
pnu_b2bt-1.1.2.dist-info/RECORD
