Metadata-Version: 2.1
Name: pnu-b2bt
Version: 1.1.2
Summary: Back to Back Testing tool
Home-page: https://github.com/HubTou/b2bt/
Author: HubTou
Author-email: nobody@nowhere.invalid
License: BSD 3-Clause License
Project-URL: Bug Tracker, https://github.com/HubTou/b2bt/issues
Keywords: pnu-project
Platform: UNKNOWN
Classifier: Development Status :: 5 - Production/Stable
Classifier: Environment :: Console
Classifier: Intended Audience :: Developers
Classifier: License :: OSI Approved :: BSD License
Classifier: Natural Language :: English
Classifier: Operating System :: OS Independent
Classifier: Operating System :: POSIX :: BSD :: FreeBSD
Classifier: Operating System :: Microsoft :: Windows
Classifier: Programming Language :: Python :: 3
Classifier: Programming Language :: Python :: 3.7
Classifier: Programming Language :: Python :: 3.8
Classifier: Programming Language :: Python :: 3.9
Classifier: Programming Language :: Python :: 3.10
Classifier: Topic :: Education :: Testing
Classifier: Topic :: Software Development
Classifier: Topic :: Software Development :: Testing
Classifier: Topic :: System
Classifier: Topic :: Utilities
Classifier: Topic :: Text Processing :: Markup :: XML
Requires-Python: >=3.7
License-File: License
Requires-Dist: colorama
Requires-Dist: defusedxml
